CHANGELOG.txt
LICENCE.txt
MANIFEST.in
README.txt
setup.py
PyEasyGame/__init__.py
pyeasygame/__init__.py
pyeasygame/logo.ico
pyeasygame.egg-info/PKG-INFO
pyeasygame.egg-info/SOURCES.txt
pyeasygame.egg-info/dependency_links.txt
pyeasygame.egg-info/requires.txt
pyeasygame.egg-info/top_level.txt