Metadata-Version: 2.1
Name: pyeasygame
Version: 3.5.3
Summary: A useful game engine for beginners
Author: Morris El Helou
Author-email: morriselhelou816@gmail.com
License-File: LICENCE.txt
